pytest_fauna/__init__.py
pytest_fauna/plugin.py
pytest_fauna-6.0.3.dist-info/LICENSE
pytest_fauna-6.0.3.dist-info/METADATA
pytest_fauna-6.0.3.dist-info/WHEEL
pytest_fauna-6.0.3.dist-info/entry_points.txt
pytest_fauna-6.0.3.dist-info/RECORD
