Metadata-Version: 2.1
Name: pytest-fauna
Version: 6.0.3
Summary: A collection of helpful test fixtures for Fauna DB.
Home-page: https://gitlab.com/munipal-oss/pytest-fauna
License: MIT
Author: Ryan Causey
Author-email: ryan.causey@munipal.io
Requires-Python: >=3.10,<4.0
Classifier: Framework :: Pytest
Classifier: License :: OSI Approved :: MIT License
Classifier: Programming Language :: Python :: 3
Classifier: Programming Language :: Python :: 3.10
Classifier: Programming Language :: Python :: 3.11
Classifier: Programming Language :: Python :: 3.12
Classifier: Programming Language :: Python :: 3.13
Provides-Extra: aws
Provides-Extra: fluctuate
Requires-Dist: fauna (>=2.0.0,<3.0.0)
Requires-Dist: fluctuate (>=4.0.0,<5.0.0) ; extra == "fluctuate"
Requires-Dist: pytest-aws-fixtures (>=3.0.0,<4.0.0) ; extra == "aws"
Requires-Dist: pytest-testinfra (>=10.1.1,<11.0.0)
Requires-Dist: python-decouple (>=3.8,<4.0)
Requires-Dist: tenacity (>=9.0.0,<10.0.0)
Project-URL: Repository, https://gitlab.com/munipal-oss/pytest-fauna
